my_sdk/__init__.py
my_sdk/client.py
my_sdk/exceptions.py
yyzz_sdk-0.1.0.dist-info/METADATA
yyzz_sdk-0.1.0.dist-info/WHEEL
yyzz_sdk-0.1.0.dist-info/RECORD
